[
	{
		"title": "Stretching",
		"body": "On the bed, as the muscles are still warm.",
		"img": "img/stretching.png"
	},
	{
		"title": "Hot water",
		"body": "Hydrate and reactivate the blood circulation.",
		"img": "img/hotwater.png"
	},
	{
		"title": "Radio Taiso",
		"body": "Calisthenics to improve posture, strength and body composition.",
		"img": "img/radiotaiso.png",
		"video": "https://www.youtube.com/embed/kM14RLTKN30"
	},
	{
		"title": "Jogging",
		"body": "Oxygene the brain, train the heart, build strong bones, strengthen muscles.",
		"img": "img/jogging.png"
	},
	{
		"title": "Power Drink",
		"body": "Great breverage to strength your immune system:\n Ginger powder, Turmeric, Cinnamon, Fenugreek, Cayenne pepper, Raw honey, Warm water.",
		"img": "img/powerdrink.png"
	},
	{
		"title": "Supplementary vitamins",
		"body": "Vitamin D for bone health and immunity.",
		"img": "img/vitamins.png"
	},
	{
		"title": "Muscle/Joint relief",
		"body": "Combine the following oils with a carrier oil and perform a self-massage: Lavender, Wintergreen, Lemon Eucalyptus.",
		"img": "img/oil.png"
	},
	{
		"title": "Mouthwash",
		"body": "Combine the following oils with alcohol, baking soda and distilled water: Clove, Tea Tree, Perppermint. Diluate with water before use.",
		"img": "img/oil.png"
	}
]
